backend/__init__.py
backend/app.py
backend/project.py
backend/data/Dump20220507.sql
backend/data/recipe_schema.sql
backend/data/recipes.db
backend/data/scraper.py
backend/data/scripts.sql
backend/data/toget.csv
food_fighters-1.0.1.dist-info/LICENSE
food_fighters-1.0.1.dist-info/METADATA
food_fighters-1.0.1.dist-info/WHEEL
food_fighters-1.0.1.dist-info/entry_points.txt
food_fighters-1.0.1.dist-info/top_level.txt
food_fighters-1.0.1.dist-info/RECORD
