Metadata-Version: 2.1
Name: food-fighters
Version: 1.0.1
Summary: API Endpoints for Food Fighters project
Home-page: UNKNOWN
Author: Food Fighters
License: MIT
Platform: UNKNOWN
Requires-Dist: Flask
Requires-Dist: Flask-SQLAlchemy
Requires-Dist: SQLAlchemy
Requires-Dist: Werkzeug
Requires-Dist: flake8
Requires-Dist: flask-restx
Requires-Dist: mysql-connector
Requires-Dist: mysql-connector-python
Requires-Dist: mysqlclient
Requires-Dist: pylint
Requires-Dist: pytest
Requires-Dist: pytest-cov
Requires-Dist: python-dotenv
Requires-Dist: recipe-scrapers
